pyROI/__init__.py
pyROI/base.py
pyROI/circle.py
pyROI/color.py
pyROI/ellipse.py
pyROI/image.py
pyROI/key.py
pyROI/point.py
pyROI/polygon.py
pyROI/rect.py
pyROI/utils.py
pyROI/window.py
pyROI/screen/__init__.py
pyROI/screen/__runner__.py
pyroi-0.3.0.dist-info/LICENSE
pyroi-0.3.0.dist-info/WHEEL
pyroi-0.3.0.dist-info/METADATA
pyroi-0.3.0.dist-info/RECORD
