Metadata-Version: 2.1
Name: pyROI
Version: 0.3.0
Summary: pyROI — A simple roi selector built by python-opencv
Author-email: Chung-Kuan Chen <b97b01045@gmail.com>
Classifier: License :: OSI Approved :: MIT License
Requires-Dist: numpy
Requires-Dist: opencv-python
Requires-Dist: dataclasses
Requires-Dist: black ; extra == "dev"
Requires-Dist: flake8 ; extra == "dev"
Requires-Dist: pre-commit ; extra == "dev"
Requires-Dist: pytest ; extra == "test"
Project-URL: Home, https://github.com/lycantrope/pyROI
Provides-Extra: dev
Provides-Extra: test
